{
  "sites": [
    {
      "key": "hongniu",
      "name": "🔵红牛资源",
      "type": 1,
      "api": "https://www.hongniuzy2.com/api.php/provide/vod/",
      "searchable": 1,
      "quickSearch": 1,
      "filterable": 1
    },
    {
      "key": "feifan",
      "name": "🔵非凡资源",
      "type": 1,
      "api": "https://cj.ffzyapi.com/api.php/provide/vod/",
      "searchable": 1,
      "quickSearch": 1,
      "filterable": 1
    },
    {
      "key": "laosebi",
      "name": "🔞老色逼资源",
      "type": 0, 
      "api": "https://apilsbzy1.com/api.php/provide/vod/at/xml",
      "searchable": 1,
      "quickSearch": 1,
      "filterable": 1
    }
  ]
}
